[
    {
        "design" : {
            "id_lego" : [
                57697
            ],
            "id_bricklink" : "57697",
            "id_rebrickable" : "57697",
            "nom_rebrickable" : "Hinge Cylinder 1 x 3 Locking with 1 Finger and Technic Friction Pin with Squared Hole",
            "statut" : "unknown"
        },
        "couleur" : {
            "statut" : "find",
            "id_couleur" : 1200
        },
        "quantite" : 4
    },
    {
        "design" : {
            "id_lego" : [
                28653,
                3023,
                6225
            ],
            "id_bricklink" : "3023",
            "id_rebrickable" : "3023",
            "nom_rebrickable" : "Plate 1 x 2",
            "statut" : "unknown"
        },
        "couleur" : {
            "statut" : "find",
            "id_couleur" : 1200
        },
        "quantite" : 2
    },
    {
        "design" : {
            "id_lego" : [
                3035
            ],
            "id_bricklink" : "3035",
            "id_rebrickable" : "3035",
            "nom_rebrickable" : "Plate 4 x 8",
            "statut" : "unknown"
        },
        "couleur" : {
            "statut" : "find",
            "id_couleur" : 1200
        },
        "quantite" : 1
    },
    {
        "design" : {
            "id_lego" : [
                32828
            ],
            "id_bricklink" : "32828",
            "id_rebrickable" : "32828",
            "nom_rebrickable" : "Plate Round 1 x 1 with Hollow Stud and Horizontal Bar 1L",
            "statut" : "unknown"
        },
        "couleur" : {
            "statut" : "find",
            "id_couleur" : 1200
        },
        "quantite" : 4
    },
    {
        "design" : {
            "id_lego" : [
                32828
            ],
            "id_bricklink" : "32828",
            "id_rebrickable" : "32828",
            "nom_rebrickable" : "Plate Round 1 x 1 with Hollow Stud and Horizontal Bar 1L",
            "statut" : "unknown"
        },
        "couleur" : {
            "statut" : "find",
            "id_couleur" : 1200
        },
        "quantite" : 1
    },
    {
        "design" : {
            "id_lego" : [
                4032
            ],
            "id_bricklink" : "4032",
            "id_rebrickable" : "4032a",
            "nom_rebrickable" : "Plate Round 2 x 2 with Axle Hole Type 1 (+ Opening)",
            "statut" : "unknown"
        },
        "couleur" : {
            "statut" : "find",
            "id_couleur" : 1200
        },
        "quantite" : 4
    },
    {
        "design" : {
            "id_lego" : [
                32062
            ],
            "id_bricklink" : "32062",
            "id_rebrickable" : "32062",
            "nom_rebrickable" : "Technic Axle 2 Notched",
            "statut" : "unknown"
        },
        "couleur" : {
            "statut" : "find",
            "id_couleur" : 1200
        },
        "quantite" : 5
    },
    {
        "design" : {
            "id_lego" : [
                41678
            ],
            "id_bricklink" : "41678",
            "id_rebrickable" : "41678",
            "nom_rebrickable" : "Technic Axle and Pin Connector Perpendicular Double Split",
            "statut" : "unknown"
        },
        "couleur" : {
            "statut" : "find",
            "id_couleur" : 1200
        },
        "quantite" : 1
    },
    {
        "design" : {
            "id_lego" : [
                28570,
                32063
            ],
            "id_bricklink" : "32063",
            "id_rebrickable" : "32063",
            "nom_rebrickable" : "Technic Beam 1 x 6 Thin",
            "statut" : "unknown"
        },
        "couleur" : {
            "statut" : "find",
            "id_couleur" : 1200
        },
        "quantite" : 2
    },
    {
        "design" : {
            "id_lego" : [
                3701
            ],
            "id_bricklink" : "3701",
            "id_rebrickable" : "3701",
            "nom_rebrickable" : "Technic Brick 1 x 4 [3 Pin Holes]",
            "statut" : "unknown"
        },
        "couleur" : {
            "statut" : "find",
            "id_couleur" : 1200
        },
        "quantite" : 2
    },
    {
        "design" : {
            "id_lego" : [
                15556,
                64567,
                86132
            ],
            "id_bricklink" : "64567",
            "id_rebrickable" : "64567",
            "nom_rebrickable" : "Weapon Lightsaber Hilt with Bottom Ring",
            "statut" : "unknown"
        },
        "couleur" : {
            "statut" : "find",
            "id_couleur" : 1200
        },
        "quantite" : 1
    },
    {
        "design" : {
            "id_lego" : [
                15556,
                64567,
                86132
            ],
            "id_bricklink" : "64567",
            "id_rebrickable" : "64567",
            "nom_rebrickable" : "Weapon Lightsaber Hilt with Bottom Ring",
            "statut" : "unknown"
        },
        "couleur" : {
            "statut" : "find",
            "id_couleur" : 1200
        },
        "quantite" : 2
    },
    {
        "design" : {
            "id_lego" : [
                3022,
                94148
            ],
            "id_bricklink" : "3022",
            "id_rebrickable" : "3022",
            "nom_rebrickable" : "Plate 2 x 2",
            "statut" : "unknown"
        },
        "couleur" : {
            "statut" : "find",
            "id_couleur" : 1404
        },
        "quantite" : 1
    },
    {
        "design" : {
            "id_lego" : [
                43093
            ],
            "id_bricklink" : "43093",
            "id_rebrickable" : "43093",
            "nom_rebrickable" : "Technic Axle Pin with Friction Ridges Lengthwise",
            "statut" : "unknown"
        },
        "couleur" : {
            "statut" : "find",
            "id_couleur" : 1404
        },
        "quantite" : 2
    },
    {
        "design" : {
            "id_lego" : [
                18274,
                28921,
                63965,
                93790
            ],
            "id_bricklink" : "63965",
            "id_rebrickable" : "63965",
            "nom_rebrickable" : "Bar 6L with Stop Ring",
            "statut" : "unknown"
        },
        "couleur" : {
            "statut" : "find",
            "id_couleur" : 1101
        },
        "quantite" : 2
    },
    {
        "design" : {
            "id_lego" : [
                15551,
                28701,
                55525,
                59900,
                64288
            ],
            "id_bricklink" : "4589b",
            "id_rebrickable" : "59900",
            "nom_rebrickable" : "Cone 1 x 1 [Top Groove]",
            "statut" : "unknown"
        },
        "couleur" : {
            "statut" : "find",
            "id_couleur" : 1101
        },
        "quantite" : 4
    },
    {
        "design" : {
            "id_lego" : [
                50337
            ],
            "id_bricklink" : "44570",
            "id_rebrickable" : "50337",
            "nom_rebrickable" : "Hinge Plate 3 x 4 Locking Dual 2 Finger, 7 teeth",
            "statut" : "unknown"
        },
        "couleur" : {
            "statut" : "find",
            "id_couleur" : 1101
        },
        "quantite" : 2
    },
    {
        "design" : {
            "id_lego" : [
                15400,
                72387
            ],
            "id_bricklink" : "15301c01",
            "id_rebrickable" : "15400",
            "nom_rebrickable" : "Launcher, Brick Special 1 x 4 Spring Shooter with Light Bluish Gray Top",
            "statut" : "unknown"
        },
        "couleur" : {
            "statut" : "find",
            "id_couleur" : 1101
        },
        "quantite" : 2
    },
    {
        "design" : {
            "id_lego" : [
                60479
            ],
            "id_bricklink" : "60479",
            "id_rebrickable" : "60479",
            "nom_rebrickable" : "Plate 1 x 12",
            "statut" : "unknown"
        },
        "couleur" : {
            "statut" : "find",
            "id_couleur" : 1101
        },
        "quantite" : 2
    },
    {
        "design" : {
            "id_lego" : [
                28653,
                3023,
                6225
            ],
            "id_bricklink" : "3023",
            "id_rebrickable" : "3023",
            "nom_rebrickable" : "Plate 1 x 2",
            "statut" : "unknown"
        },
        "couleur" : {
            "statut" : "find",
            "id_couleur" : 1101
        },
        "quantite" : 6
    },
    {
        "design" : {
            "id_lego" : [
                3666
            ],
            "id_bricklink" : "3666",
            "id_rebrickable" : "3666",
            "nom_rebrickable" : "Plate 1 x 6",
            "statut" : "unknown"
        },
        "couleur" : {
            "statut" : "find",
            "id_couleur" : 1101
        },
        "quantite" : 2
    },
    {
        "design" : {
            "id_lego" : [
                3022,
                94148
            ],
            "id_bricklink" : "3022",
            "id_rebrickable" : "3022",
            "nom_rebrickable" : "Plate 2 x 2",
            "statut" : "unknown"
        },
        "couleur" : {
            "statut" : "find",
            "id_couleur" : 1101
        },
        "quantite" : 1
    },
    {
        "design" : {
            "id_lego" : [
                3020,
                5584
            ],
            "id_bricklink" : "3020",
            "id_rebrickable" : "3020",
            "nom_rebrickable" : "Plate 2 x 4",
            "statut" : "unknown"
        },
        "couleur" : {
            "statut" : "find",
            "id_couleur" : 1101
        },
        "quantite" : 11
    },
    {
        "design" : {
            "id_lego" : [
                3034
            ],
            "id_bricklink" : "3034",
            "id_rebrickable" : "3034",
            "nom_rebrickable" : "Plate 2 x 8",
            "statut" : "unknown"
        },
        "couleur" : {
            "statut" : "find",
            "id_couleur" : 1101
        },
        "quantite" : 1
    },
    {
        "design" : {
            "id_lego" : [
                15570,
                30057,
                34823,
                39799,
                44325,
                51809,
                6141
            ],
            "id_bricklink" : "4073",
            "id_rebrickable" : "6141",
            "nom_rebrickable" : "Plate Round 1 x 1 with Solid Stud",
            "statut" : "unknown"
        },
        "couleur" : {
            "statut" : "find",
            "id_couleur" : 1101
        },
        "quantite" : 1
    },
    {
        "design" : {
            "id_lego" : [
                15570,
                30057,
                34823,
                39799,
                44325,
                51809,
                6141
            ],
            "id_bricklink" : "4073",
            "id_rebrickable" : "6141",
            "nom_rebrickable" : "Plate Round 1 x 1 with Solid Stud",
            "statut" : "unknown"
        },
        "couleur" : {
            "statut" : "find",
            "id_couleur" : 1101
        },
        "quantite" : 4
    },
    {
        "design" : {
            "id_lego" : [
                52738,
                61252
            ],
            "id_bricklink" : "61252",
            "id_rebrickable" : "61252",
            "nom_rebrickable" : "Plate Special 1 x 1 with Clip Horizontal [Thick Open O Clip]",
            "statut" : "unknown"
        },
        "couleur" : {
            "statut" : "find",
            "id_couleur" : 1101
        },
        "quantite" : 4
    },
    {
        "design" : {
            "id_lego" : [
                15573,
                78823
            ],
            "id_bricklink" : "15573",
            "id_rebrickable" : "15573",
            "nom_rebrickable" : "Plate Special 1 x 2 with 1 Stud with Groove and Inside Stud Holder (Jumper)",
            "statut" : "unknown"
        },
        "couleur" : {
            "statut" : "find",
            "id_couleur" : 1101
        },
        "quantite" : 3
    },
    {
        "design" : {
            "id_lego" : [
                92593
            ],
            "id_bricklink" : "92593",
            "id_rebrickable" : "92593",
            "nom_rebrickable" : "Plate Special 1 x 4 with 2 Studs",
            "statut" : "unknown"
        },
        "couleur" : {
            "statut" : "find",
            "id_couleur" : 1101
        },
        "quantite" : 2
    },
    {
        "design" : {
            "id_lego" : [
                83473,
                85984
            ],
            "id_bricklink" : "85984",
            "id_rebrickable" : "85984",
            "nom_rebrickable" : "Slope 30° 1 x 2 x 2/3",
            "statut" : "unknown"
        },
        "couleur" : {
            "statut" : "find",
            "id_couleur" : 1101
        },
        "quantite" : 2
    },
    {
        "design" : {
            "id_lego" : [
                100425,
                28192,
                39729,
                78566
            ],
            "id_bricklink" : "28192",
            "id_rebrickable" : "28192",
            "nom_rebrickable" : "Slope 45° 2 x 1 with 2/3 Inverted Cutout and no stud",
            "statut" : "unknown"
        },
        "couleur" : {
            "statut" : "find",
            "id_couleur" : 1101
        },
        "quantite" : 2
    },
    {
        "design" : {
            "id_lego" : [
                11477,
                17134,
                3593,
                67128
            ],
            "id_bricklink" : "11477",
            "id_rebrickable" : "11477",
            "nom_rebrickable" : "Slope Curved 2 x 1 No Studs [1/2 Bow]",
            "statut" : "unknown"
        },
        "couleur" : {
            "statut" : "find",
            "id_couleur" : 1101
        },
        "quantite" : 2
    },
    {
        "design" : {
            "id_lego" : [
                3747
            ],
            "id_bricklink" : "3747b",
            "id_rebrickable" : "3747b",
            "nom_rebrickable" : "Slope Inverted 33° 3 x 2 [Connections between Studs]",
            "statut" : "unknown"
        },
        "couleur" : {
            "statut" : "find",
            "id_couleur" : 1101
        },
        "quantite" : 2
    },
    {
        "design" : {
            "id_lego" : [
                3676
            ],
            "id_bricklink" : "3676",
            "id_rebrickable" : "3676",
            "nom_rebrickable" : "Slope Inverted 45° 2 x 2 Double Convex",
            "statut" : "unknown"
        },
        "couleur" : {
            "statut" : "find",
            "id_couleur" : 1101
        },
        "quantite" : 2
    },
    {
        "design" : {
            "id_lego" : [
                40146,
                6536
            ],
            "id_bricklink" : "6536",
            "id_rebrickable" : "6536",
            "nom_rebrickable" : "Technic Axle and Pin Connector Perpendicular",
            "statut" : "unknown"
        },
        "couleur" : {
            "statut" : "find",
            "id_couleur" : 1101
        },
        "quantite" : 1
    },
    {
        "design" : {
            "id_lego" : [
                59443
            ],
            "id_bricklink" : "6538c",
            "id_rebrickable" : "59443",
            "nom_rebrickable" : "Technic Axle Connector Smooth [with x Hole + Orientation]",
            "statut" : "unknown"
        },
        "couleur" : {
            "statut" : "find",
            "id_couleur" : 1101
        },
        "quantite" : 2
    },
    {
        "design" : {
            "id_lego" : [
                3700
            ],
            "id_bricklink" : "3700",
            "id_rebrickable" : "3700",
            "nom_rebrickable" : "Technic Brick 1 x 2 [1 Pin Hole]",
            "statut" : "unknown"
        },
        "couleur" : {
            "statut" : "find",
            "id_couleur" : 1101
        },
        "quantite" : 1
    },
    {
        "design" : {
            "id_lego" : [
                1136,
                3068,
                63327,
                78814
            ],
            "id_bricklink" : "3068",
            "id_rebrickable" : "3068b",
            "nom_rebrickable" : "Tile 2 x 2 with Groove",
            "statut" : "unknown"
        },
        "couleur" : {
            "statut" : "find",
            "id_couleur" : 1101
        },
        "quantite" : 1
    },
    {
        "design" : {
            "id_lego" : [
                15535
            ],
            "id_bricklink" : "15535",
            "id_rebrickable" : "15535",
            "nom_rebrickable" : "Tile Round 2 x 2 with Hole",
            "statut" : "unknown"
        },
        "couleur" : {
            "statut" : "find",
            "id_couleur" : 1101
        },
        "quantite" : 2
    },
    {
        "design" : {
            "id_lego" : [
                15561,
                2412,
                30244,
                35248,
                51815,
                71957,
                72582,
                78812
            ],
            "id_bricklink" : "2412b",
            "id_rebrickable" : "2412b",
            "nom_rebrickable" : "Tile Special 1 x 2 Grille with Bottom Groove",
            "statut" : "unknown"
        },
        "couleur" : {
            "statut" : "find",
            "id_couleur" : 1101
        },
        "quantite" : 4
    },
    {
        "design" : {
            "id_lego" : [
                24299
            ],
            "id_bricklink" : "24299",
            "id_rebrickable" : "24299",
            "nom_rebrickable" : "Wedge Plate 2 x 2 Left",
            "statut" : "unknown"
        },
        "couleur" : {
            "statut" : "find",
            "id_couleur" : 1101
        },
        "quantite" : 1
    },
    {
        "design" : {
            "id_lego" : [
                24307
            ],
            "id_bricklink" : "24307",
            "id_rebrickable" : "24307",
            "nom_rebrickable" : "Wedge Plate 2 x 2 Right",
            "statut" : "unknown"
        },
        "couleur" : {
            "statut" : "find",
            "id_couleur" : 1101
        },
        "quantite" : 1
    },
    {
        "design" : {
            "id_lego" : [
                51739
            ],
            "id_bricklink" : "51739",
            "id_rebrickable" : "51739",
            "nom_rebrickable" : "Wedge Plate 2 x 4",
            "statut" : "unknown"
        },
        "couleur" : {
            "statut" : "find",
            "id_couleur" : 1101
        },
        "quantite" : 2
    },
    {
        "design" : {
            "id_lego" : [
                13670,
                6587
            ],
            "id_bricklink" : "6587",
            "id_rebrickable" : "6587",
            "nom_rebrickable" : "Technic Axle 3 with Stud",
            "statut" : "unknown"
        },
        "couleur" : {
            "statut" : "find",
            "id_couleur" : 1709
        },
        "quantite" : 1
    },
    {
        "design" : {
            "id_lego" : [
                21462,
                28697,
                30374
            ],
            "id_bricklink" : "30374",
            "id_rebrickable" : "30374",
            "nom_rebrickable" : "Bar 4L (Lightsaber Blade / Wand)",
            "statut" : "unknown"
        },
        "couleur" : {
            "statut" : "find",
            "id_couleur" : 1102
        },
        "quantite" : 4
    },
    {
        "design" : {
            "id_lego" : [
                11215
            ],
            "id_bricklink" : "11215",
            "id_rebrickable" : "11215",
            "nom_rebrickable" : "Bracket 5 x 2 x 1 1/3 with Holes, Pin Bottom",
            "statut" : "unknown"
        },
        "couleur" : {
            "statut" : "find",
            "id_couleur" : 1102
        },
        "quantite" : 4
    },
    {
        "design" : {
            "id_lego" : [
                53540
            ],
            "id_bricklink" : "30526",
            "id_rebrickable" : "53540",
            "nom_rebrickable" : "Brick Special 1 x 2 with 2 Pins, Square Pin Holes",
            "statut" : "unknown"
        },
        "couleur" : {
            "statut" : "find",
            "id_couleur" : 1102
        },
        "quantite" : 2
    },
    {
        "design" : {
            "id_lego" : [
                28554,
                30008,
                3024,
                63326
            ],
            "id_bricklink" : "3024",
            "id_rebrickable" : "3024",
            "nom_rebrickable" : "Plate 1 x 1",
            "statut" : "unknown"
        },
        "couleur" : {
            "statut" : "find",
            "id_couleur" : 1102
        },
        "quantite" : 1
    },
    {
        "design" : {
            "id_lego" : [
                28554,
                30008,
                3024,
                63326
            ],
            "id_bricklink" : "3024",
            "id_rebrickable" : "3024",
            "nom_rebrickable" : "Plate 1 x 1",
            "statut" : "unknown"
        },
        "couleur" : {
            "statut" : "find",
            "id_couleur" : 1102
        },
        "quantite" : 2
    },
    {
        "design" : {
            "id_lego" : [
                3710
            ],
            "id_bricklink" : "3710",
            "id_rebrickable" : "3710",
            "nom_rebrickable" : "Plate 1 x 4",
            "statut" : "unknown"
        },
        "couleur" : {
            "statut" : "find",
            "id_couleur" : 1102
        },
        "quantite" : 13
    },
    {
        "design" : {
            "id_lego" : [
                3666
            ],
            "id_bricklink" : "3666",
            "id_rebrickable" : "3666",
            "nom_rebrickable" : "Plate 1 x 6",
            "statut" : "unknown"
        },
        "couleur" : {
            "statut" : "find",
            "id_couleur" : 1102
        },
        "quantite" : 2
    },
    {
        "design" : {
            "id_lego" : [
                2445
            ],
            "id_bricklink" : "2445",
            "id_rebrickable" : "2445",
            "nom_rebrickable" : "Plate 2 x 12",
            "statut" : "unknown"
        },
        "couleur" : {
            "statut" : "find",
            "id_couleur" : 1102
        },
        "quantite" : 1
    },
    {
        "design" : {
            "id_lego" : [
                3021
            ],
            "id_bricklink" : "3021",
            "id_rebrickable" : "3021",
            "nom_rebrickable" : "Plate 2 x 3",
            "statut" : "unknown"
        },
        "couleur" : {
            "statut" : "find",
            "id_couleur" : 1102
        },
        "quantite" : 8
    },
    {
        "design" : {
            "id_lego" : [
                3795
            ],
            "id_bricklink" : "3795",
            "id_rebrickable" : "3795",
            "nom_rebrickable" : "Plate 2 x 6",
            "statut" : "unknown"
        },
        "couleur" : {
            "statut" : "find",
            "id_couleur" : 1102
        },
        "quantite" : 1
    },
    {
        "design" : {
            "id_lego" : [
                11212
            ],
            "id_bricklink" : "11212",
            "id_rebrickable" : "11212",
            "nom_rebrickable" : "Plate 3 x 3",
            "statut" : "unknown"
        },
        "couleur" : {
            "statut" : "find",
            "id_couleur" : 1102
        },
        "quantite" : 2
    },
    {
        "design" : {
            "id_lego" : [
                2654,
                28558,
                54196,
                93791
            ],
            "id_bricklink" : "2654",
            "id_rebrickable" : "2654",
            "nom_rebrickable" : "Plate Round 2 x 2 with Rounded Bottom [Boat Stud]",
            "statut" : "unknown"
        },
        "couleur" : {
            "statut" : "find",
            "id_couleur" : 1102
        },
        "quantite" : 4
    },
    {
        "design" : {
            "id_lego" : [
                4081,
                41632
            ],
            "id_bricklink" : "4081b",
            "id_rebrickable" : "4081b",
            "nom_rebrickable" : "Plate Special 1 x 1 with Clip Light, Bar Hole [Thick Ring]",
            "statut" : "unknown"
        },
        "couleur" : {
            "statut" : "find",
            "id_couleur" : 1102
        },
        "quantite" : 4
    },
    {
        "design" : {
            "id_lego" : [
                44860,
                5731,
                60897,
                93793
            ],
            "id_bricklink" : "4085d",
            "id_rebrickable" : "60897",
            "nom_rebrickable" : "Plate Special 1 x 1 with Clip Vertical [Thick Open O Clip]",
            "statut" : "unknown"
        },
        "couleur" : {
            "statut" : "find",
            "id_couleur" : 1102
        },
        "quantite" : 8
    },
    {
        "design" : {
            "id_lego" : [
                42923,
                63868
            ],
            "id_bricklink" : "63868",
            "id_rebrickable" : "63868",
            "nom_rebrickable" : "Plate Special 1 x 2 with Clip Horizontal on End",
            "statut" : "unknown"
        },
        "couleur" : {
            "statut" : "find",
            "id_couleur" : 1102
        },
        "quantite" : 2
    },
    {
        "design" : {
            "id_lego" : [
                100767,
                33909
            ],
            "id_bricklink" : "33909",
            "id_rebrickable" : "33909",
            "nom_rebrickable" : "Plate Special 2 x 2 with Only 2 studs",
            "statut" : "unknown"
        },
        "couleur" : {
            "statut" : "find",
            "id_couleur" : 1102
        },
        "quantite" : 1
    },
    {
        "design" : {
            "id_lego" : [
                32803
            ],
            "id_bricklink" : "32803",
            "id_rebrickable" : "32803",
            "nom_rebrickable" : "Slope Curved 2 x 2 x 2/3 Inverted",
            "statut" : "unknown"
        },
        "couleur" : {
            "statut" : "find",
            "id_couleur" : 1102
        },
        "quantite" : 2
    },
    {
        "design" : {
            "id_lego" : [
                31493,
                32064
            ],
            "id_bricklink" : "32064",
            "id_rebrickable" : "32064a",
            "nom_rebrickable" : "Technic Brick 1 x 2 with Axle Hole Type 1 [+ Opening] and Bottom Pin",
            "statut" : "unknown"
        },
        "couleur" : {
            "statut" : "find",
            "id_couleur" : 1102
        },
        "quantite" : 1
    },
    {
        "design" : {
            "id_lego" : [
                42798,
                6590
            ],
            "id_bricklink" : "3713",
            "id_rebrickable" : "3713",
            "nom_rebrickable" : "Technic Bush",
            "statut" : "unknown"
        },
        "couleur" : {
            "statut" : "find",
            "id_couleur" : 1102
        },
        "quantite" : 1
    },
    {
        "design" : {
            "id_lego" : [
                42798,
                6590
            ],
            "id_bricklink" : "3713",
            "id_rebrickable" : "3713",
            "nom_rebrickable" : "Technic Bush",
            "statut" : "unknown"
        },
        "couleur" : {
            "statut" : "find",
            "id_couleur" : 1102
        },
        "quantite" : 1
    },
    {
        "design" : {
            "id_lego" : [
                4274
            ],
            "id_bricklink" : "4274",
            "id_rebrickable" : "4274",
            "nom_rebrickable" : "Technic Pin 1/2",
            "statut" : "unknown"
        },
        "couleur" : {
            "statut" : "find",
            "id_couleur" : 1102
        },
        "quantite" : 1
    },
    {
        "design" : {
            "id_lego" : [
                4274
            ],
            "id_bricklink" : "4274",
            "id_rebrickable" : "4274",
            "nom_rebrickable" : "Technic Pin 1/2",
            "statut" : "unknown"
        },
        "couleur" : {
            "statut" : "find",
            "id_couleur" : 1102
        },
        "quantite" : 1
    },
    {
        "design" : {
            "id_lego" : [
                3673
            ],
            "id_bricklink" : "3673",
            "id_rebrickable" : "3673",
            "nom_rebrickable" : "Technic Pin without Friction Ridges Lengthwise",
            "statut" : "unknown"
        },
        "couleur" : {
            "statut" : "find",
            "id_couleur" : 1102
        },
        "quantite" : 1
    },
    {
        "design" : {
            "id_lego" : [
                3673
            ],
            "id_bricklink" : "3673",
            "id_rebrickable" : "3673",
            "nom_rebrickable" : "Technic Pin without Friction Ridges Lengthwise",
            "statut" : "unknown"
        },
        "couleur" : {
            "statut" : "find",
            "id_couleur" : 1102
        },
        "quantite" : 1
    },
    {
        "design" : {
            "id_lego" : [
                38879,
                87079
            ],
            "id_bricklink" : "87079",
            "id_rebrickable" : "87079",
            "nom_rebrickable" : "Tile 2 x 4 with Groove",
            "statut" : "unknown"
        },
        "couleur" : {
            "statut" : "find",
            "id_couleur" : 1102
        },
        "quantite" : 2
    },
    {
        "design" : {
            "id_lego" : [
                35380,
                35381,
                39797,
                98138
            ],
            "id_bricklink" : "98138",
            "id_rebrickable" : "98138",
            "nom_rebrickable" : "Tile Round 1 x 1",
            "statut" : "unknown"
        },
        "couleur" : {
            "statut" : "find",
            "id_couleur" : 1102
        },
        "quantite" : 1
    },
    {
        "design" : {
            "id_lego" : [
                35380,
                35381,
                39797,
                98138
            ],
            "id_bricklink" : "98138",
            "id_rebrickable" : "98138",
            "nom_rebrickable" : "Tile Round 1 x 1",
            "statut" : "unknown"
        },
        "couleur" : {
            "statut" : "find",
            "id_couleur" : 1102
        },
        "quantite" : 1
    },
    {
        "design" : {
            "id_lego" : [
                112416,
                22385,
                35339,
                35341,
                67130
            ],
            "id_bricklink" : "22385",
            "id_rebrickable" : "22385",
            "nom_rebrickable" : "Tile Special 2 x 3 Pentagonal",
            "statut" : "unknown"
        },
        "couleur" : {
            "statut" : "find",
            "id_couleur" : 1102
        },
        "quantite" : 2
    },
    {
        "design" : {
            "id_lego" : [
                43723
            ],
            "id_bricklink" : "43723",
            "id_rebrickable" : "43723",
            "nom_rebrickable" : "Wedge Plate 3 x 2 Left",
            "statut" : "unknown"
        },
        "couleur" : {
            "statut" : "find",
            "id_couleur" : 1102
        },
        "quantite" : 3
    },
    {
        "design" : {
            "id_lego" : [
                43722
            ],
            "id_bricklink" : "43722",
            "id_rebrickable" : "43722",
            "nom_rebrickable" : "Wedge Plate 3 x 2 Right",
            "statut" : "unknown"
        },
        "couleur" : {
            "statut" : "find",
            "id_couleur" : 1102
        },
        "quantite" : 3
    },
    {
        "design" : {
            "id_lego" : [
                28842,
                4859,
                90194
            ],
            "id_bricklink" : "48183",
            "id_rebrickable" : "90194",
            "nom_rebrickable" : "Wedge Plate 3 x 4 with Stud Notches [Reinforced Underside]",
            "statut" : "unknown"
        },
        "couleur" : {
            "statut" : "find",
            "id_couleur" : 1102
        },
        "quantite" : 2
    },
    {
        "design" : {
            "id_lego" : [
                30503
            ],
            "id_bricklink" : "30503",
            "id_rebrickable" : "30503",
            "nom_rebrickable" : "Wedge Plate 4 x 4 Cut Corner",
            "statut" : "unknown"
        },
        "couleur" : {
            "statut" : "find",
            "id_couleur" : 1102
        },
        "quantite" : 4
    },
    {
        "design" : {
            "id_lego" : [
                15556,
                64567,
                86132
            ],
            "id_bricklink" : "64567",
            "id_rebrickable" : "64567",
            "nom_rebrickable" : "Weapon Lightsaber Hilt with Bottom Ring",
            "statut" : "unknown"
        },
        "couleur" : {
            "statut" : "find",
            "id_couleur" : 2103
        },
        "quantite" : 1
    },
    {
        "design" : {
            "id_lego" : [
                15556,
                64567,
                86132
            ],
            "id_bricklink" : "64567",
            "id_rebrickable" : "64567",
            "nom_rebrickable" : "Weapon Lightsaber Hilt with Bottom Ring",
            "statut" : "unknown"
        },
        "couleur" : {
            "statut" : "find",
            "id_couleur" : 2103
        },
        "quantite" : 1
    },
    {
        "design" : {
            "id_lego" : [
            ],
            "id_bricklink" : "75281stk01",
            "id_rebrickable" : "69117",
            "nom_rebrickable" : "Sticker Sheet for Set 75281-1",
            "statut" : "unknown"
        },
        "couleur" : {
            "nom_lego" : null,
            "id_bricklink" : 0,
            "nom_bricklink" : [
                "(Not Applicable)"
            ],
            "id_rebrickable" : 9999,
            "nom_rebrickable" : "[No Color/Any Color]",
            "statut" : "unknown"
        },
        "quantite" : 1
    },
    {
        "design" : {
            "id_lego" : [
                3022,
                94148
            ],
            "id_bricklink" : "3022",
            "id_rebrickable" : "3022",
            "nom_rebrickable" : "Plate 2 x 2",
            "statut" : "unknown"
        },
        "couleur" : {
            "statut" : "find",
            "id_couleur" : 1901
        },
        "quantite" : 1
    },
    {
        "design" : {
            "id_lego" : [
                15573,
                78823
            ],
            "id_bricklink" : "15573",
            "id_rebrickable" : "15573",
            "nom_rebrickable" : "Plate Special 1 x 2 with 1 Stud with Groove and Inside Stud Holder (Jumper)",
            "statut" : "unknown"
        },
        "couleur" : {
            "statut" : "find",
            "id_couleur" : 1708
        },
        "quantite" : 1
    },
    {
        "design" : {
            "id_lego" : [
                18862,
                33847,
                35338,
                50746,
                54200,
                63290
            ],
            "id_bricklink" : "54200",
            "id_rebrickable" : "54200",
            "nom_rebrickable" : "Slope 30° 1 x 1 x 2/3 (Cheese Slope)",
            "statut" : "unknown"
        },
        "couleur" : {
            "statut" : "find",
            "id_couleur" : 1708
        },
        "quantite" : 1
    },
    {
        "design" : {
            "id_lego" : [
                18862,
                33847,
                35338,
                50746,
                54200,
                63290
            ],
            "id_bricklink" : "54200",
            "id_rebrickable" : "54200",
            "nom_rebrickable" : "Slope 30° 1 x 1 x 2/3 (Cheese Slope)",
            "statut" : "unknown"
        },
        "couleur" : {
            "statut" : "find",
            "id_couleur" : 1708
        },
        "quantite" : 1
    },
    {
        "design" : {
            "id_lego" : [
                83473,
                85984
            ],
            "id_bricklink" : "85984",
            "id_rebrickable" : "85984",
            "nom_rebrickable" : "Slope 30° 1 x 2 x 2/3",
            "statut" : "unknown"
        },
        "couleur" : {
            "statut" : "find",
            "id_couleur" : 1708
        },
        "quantite" : 2
    },
    {
        "design" : {
            "id_lego" : [
                15303,
                29340
            ],
            "id_bricklink" : "15303",
            "id_rebrickable" : "15303",
            "nom_rebrickable" : "Projectile, Spring Shooter Ammunition 8L Bar",
            "statut" : "unknown"
        },
        "couleur" : {
            "statut" : "find",
            "id_couleur" : 1551
        },
        "quantite" : 3
    },
    {
        "design" : {
            "id_lego" : [
                51956
            ],
            "id_bricklink" : "35394pb001",
            "id_rebrickable" : "35394pr0003",
            "nom_rebrickable" : "Dish 4 x 4 Inverted with Open Stud [Radar] with Cockpit Print",
            "statut" : "unknown"
        },
        "couleur" : {
            "statut" : "find",
            "id_couleur" : 1750
        },
        "quantite" : 1
    },
    {
        "design" : {
            "id_lego" : [
                73856
            ],
            "id_bricklink" : "10312pb08",
            "id_rebrickable" : "10312pr0009",
            "nom_rebrickable" : "Windscreen 10 x 6 x 3 Bubble Canopy Double Tapered with Square Front Cutout - Jedi Interceptor print",
            "statut" : "unknown"
        },
        "couleur" : {
            "statut" : "find",
            "id_couleur" : 1750
        },
        "quantite" : 1
    },
    {
        "design" : {
            "id_lego" : [
                21462,
                28697,
                30374
            ],
            "id_bricklink" : "30374",
            "id_rebrickable" : "30374",
            "nom_rebrickable" : "Bar 4L (Lightsaber Blade / Wand)",
            "statut" : "unknown"
        },
        "couleur" : {
            "statut" : "find",
            "id_couleur" : 1453
        },
        "quantite" : 1
    },
    {
        "design" : {
            "id_lego" : [
                111473,
                112025,
                17964,
                22669,
                30063,
                35395,
                4740,
                64938,
                71874
            ],
            "id_bricklink" : "4740",
            "id_rebrickable" : "4740",
            "nom_rebrickable" : "Dish 2 x 2 Inverted [Radar]",
            "statut" : "unknown"
        },
        "couleur" : {
            "statut" : "find",
            "id_couleur" : 1453
        },
        "quantite" : 2
    },
    {
        "design" : {
            "id_lego" : [
                99781
            ],
            "id_bricklink" : "99781",
            "id_rebrickable" : "99781",
            "nom_rebrickable" : "Bracket 1 x 2 - 1 x 2",
            "statut" : "unknown"
        },
        "couleur" : {
            "statut" : "find",
            "id_couleur" : 1601
        },
        "quantite" : 2
    },
    {
        "design" : {
            "id_lego" : [
                3010
            ],
            "id_bricklink" : "3010",
            "id_rebrickable" : "3010",
            "nom_rebrickable" : "Brick 1 x 4",
            "statut" : "unknown"
        },
        "couleur" : {
            "statut" : "find",
            "id_couleur" : 1601
        },
        "quantite" : 1
    },
    {
        "design" : {
            "id_lego" : [
                17979,
                53913
            ],
            "id_bricklink" : "x1435",
            "id_rebrickable" : "17979",
            "nom_rebrickable" : "Flag 5 x 6 Hexagonal with U Clips",
            "statut" : "unknown"
        },
        "couleur" : {
            "statut" : "find",
            "id_couleur" : 1601
        },
        "quantite" : 4
    },
    {
        "design" : {
            "id_lego" : [
                28653,
                3023,
                6225
            ],
            "id_bricklink" : "3023",
            "id_rebrickable" : "3023",
            "nom_rebrickable" : "Plate 1 x 2",
            "statut" : "unknown"
        },
        "couleur" : {
            "statut" : "find",
            "id_couleur" : 1601
        },
        "quantite" : 5
    },
    {
        "design" : {
            "id_lego" : [
                3034
            ],
            "id_bricklink" : "3034",
            "id_rebrickable" : "3034",
            "nom_rebrickable" : "Plate 2 x 8",
            "statut" : "unknown"
        },
        "couleur" : {
            "statut" : "find",
            "id_couleur" : 1601
        },
        "quantite" : 2
    },
    {
        "design" : {
            "id_lego" : [
                24201
            ],
            "id_bricklink" : "24201",
            "id_rebrickable" : "24201",
            "nom_rebrickable" : "Slope Curved 2 x 1 Inverted",
            "statut" : "unknown"
        },
        "couleur" : {
            "statut" : "find",
            "id_couleur" : 1601
        },
        "quantite" : 8
    },
    {
        "design" : {
            "id_lego" : [
                112417,
                63324,
                6636,
                75702
            ],
            "id_bricklink" : "6636",
            "id_rebrickable" : "6636",
            "nom_rebrickable" : "Tile 1 x 6 with Groove",
            "statut" : "unknown"
        },
        "couleur" : {
            "statut" : "find",
            "id_couleur" : 1601
        },
        "quantite" : 4
    },
    {
        "design" : {
            "id_lego" : [
                15561,
                2412,
                30244,
                35248,
                51815,
                71957,
                72582,
                78812
            ],
            "id_bricklink" : "2412b",
            "id_rebrickable" : "2412b",
            "nom_rebrickable" : "Tile Special 1 x 2 Grille with Bottom Groove",
            "statut" : "unknown"
        },
        "couleur" : {
            "statut" : "find",
            "id_couleur" : 1601
        },
        "quantite" : 4
    },
    {
        "design" : {
            "id_lego" : [
                24299
            ],
            "id_bricklink" : "24299",
            "id_rebrickable" : "24299",
            "nom_rebrickable" : "Wedge Plate 2 x 2 Left",
            "statut" : "unknown"
        },
        "couleur" : {
            "statut" : "find",
            "id_couleur" : 1601
        },
        "quantite" : 2
    },
    {
        "design" : {
            "id_lego" : [
                24307
            ],
            "id_bricklink" : "24307",
            "id_rebrickable" : "24307",
            "nom_rebrickable" : "Wedge Plate 2 x 2 Right",
            "statut" : "unknown"
        },
        "couleur" : {
            "statut" : "find",
            "id_couleur" : 1601
        },
        "quantite" : 2
    },
    {
        "design" : {
            "id_lego" : [
                51739
            ],
            "id_bricklink" : "51739",
            "id_rebrickable" : "51739",
            "nom_rebrickable" : "Wedge Plate 2 x 4",
            "statut" : "unknown"
        },
        "couleur" : {
            "statut" : "find",
            "id_couleur" : 1601
        },
        "quantite" : 2
    },
    {
        "design" : {
            "id_lego" : [
                50305
            ],
            "id_bricklink" : "50305",
            "id_rebrickable" : "50305",
            "nom_rebrickable" : "Wedge Plate 8 x 3, 22° Left",
            "statut" : "unknown"
        },
        "couleur" : {
            "statut" : "find",
            "id_couleur" : 1601
        },
        "quantite" : 1
    },
    {
        "design" : {
            "id_lego" : [
                50304
            ],
            "id_bricklink" : "50304",
            "id_rebrickable" : "50304",
            "nom_rebrickable" : "Wedge Plate 8 x 3, 22° Right",
            "statut" : "unknown"
        },
        "couleur" : {
            "statut" : "find",
            "id_couleur" : 1601
        },
        "quantite" : 1
    },
    {
        "design" : {
            "id_lego" : [
                43710
            ],
            "id_bricklink" : "43710",
            "id_rebrickable" : "43710",
            "nom_rebrickable" : "Wedge Sloped 4 x 2 Triple Left",
            "statut" : "unknown"
        },
        "couleur" : {
            "statut" : "find",
            "id_couleur" : 1601
        },
        "quantite" : 2
    },
    {
        "design" : {
            "id_lego" : [
                43711
            ],
            "id_bricklink" : "43711",
            "id_rebrickable" : "43711",
            "nom_rebrickable" : "Wedge Sloped 4 x 2 Triple Right",
            "statut" : "unknown"
        },
        "couleur" : {
            "statut" : "find",
            "id_couleur" : 1601
        },
        "quantite" : 2
    }
]